lasso/__init__.py
lasso/reports/VERSION.txt
lasso/reports/__init__.py
lasso/reports/argparse.py
lasso/reports/branches/__init__.py
lasso/reports/branches/git_actions.py
lasso/reports/branches/git_ping.py
lasso/reports/corral/__init__.py
lasso/reports/corral/cattle_head.py
lasso/reports/corral/herd.py
lasso/reports/gh_pages/__init__.py
lasso/reports/gh_pages/build_summaries.py
lasso/reports/gh_pages/root_index.py
lasso/reports/gh_pages/summary.py
lasso/reports/gh_pages/resources/_config.yml
lasso/reports/gh_pages/resources/images/changelog.png
lasso/reports/gh_pages/resources/images/changelog_text.png
lasso/reports/gh_pages/resources/images/download.png
lasso/reports/gh_pages/resources/images/download_text.png
lasso/reports/gh_pages/resources/images/feedback.png
lasso/reports/gh_pages/resources/images/feedback_text.png
lasso/reports/gh_pages/resources/images/license.png
lasso/reports/gh_pages/resources/images/license_text.png
lasso/reports/gh_pages/resources/images/logo.png
lasso/reports/gh_pages/resources/images/manual.png
lasso/reports/gh_pages/resources/images/manual_text.png
lasso/reports/gh_pages/resources/images/requirements.png
lasso/reports/gh_pages/resources/images/requirements_text.png
lasso/reports/plan/__init__.py
lasso/reports/plan/plan.py
lasso/reports/plan/plan.template.rst
lasso/reports/sloc/__init__.py
lasso/reports/sloc/sloc.py
lasso/reports/tags/__init__.py
lasso/reports/tags/tags.py
lasso/reports/zenhub/__init__.py
lasso/reports/zenhub/zenhub.py
lasso_reports-2.0.0.dist-info/licenses/LICENSE.md
lasso_reports-2.0.0.dist-info/licenses/NOTICE.txt
lasso_reports-2.0.0.dist-info/METADATA
lasso_reports-2.0.0.dist-info/WHEEL
lasso_reports-2.0.0.dist-info/entry_points.txt
lasso_reports-2.0.0.dist-info/top_level.txt
lasso_reports-2.0.0.dist-info/zip-safe
lasso_reports-2.0.0.dist-info/RECORD
